ocsf/__init__.py
ocsf/_base.py
ocsf/py.typed
ocsf/v1_0_0/__init__.py
ocsf/v1_0_0/enums/__init__.py
ocsf/v1_0_0/enums/activity_id.py
ocsf/v1_0_0/enums/algorithm_id.py
ocsf/v1_0_0/enums/auth_protocol_id.py
ocsf/v1_0_0/enums/boundary_id.py
ocsf/v1_0_0/enums/category_ids.py
ocsf/v1_0_0/enums/classification_ids.py
ocsf/v1_0_0/enums/confidence_id.py
ocsf/v1_0_0/enums/confidentiality_id.py
ocsf/v1_0_0/enums/depth.py
ocsf/v1_0_0/enums/direction_id.py
ocsf/v1_0_0/enums/flag_ids.py
ocsf/v1_0_0/enums/http_method.py
ocsf/v1_0_0/enums/impact_id.py
ocsf/v1_0_0/enums/injection_type_id.py
ocsf/v1_0_0/enums/integrity_id.py
ocsf/v1_0_0/enums/load_type_id.py
ocsf/v1_0_0/enums/logon_type_id.py
ocsf/v1_0_0/enums/opcode_id.py
ocsf/v1_0_0/enums/phase_id.py
ocsf/v1_0_0/enums/protocol_ver_id.py
ocsf/v1_0_0/enums/rcode_id.py
ocsf/v1_0_0/enums/risk_level_id.py
ocsf/v1_0_0/enums/run_state_id.py
ocsf/v1_0_0/enums/score_id.py
ocsf/v1_0_0/enums/severity_id.py
ocsf/v1_0_0/enums/share_type_id.py
ocsf/v1_0_0/enums/state_id.py
ocsf/v1_0_0/enums/status_id.py
ocsf/v1_0_0/enums/type_id.py
ocsf/v1_0_0/events/__init__.py
ocsf/v1_0_0/events/account_change.py
ocsf/v1_0_0/events/api_activity.py
ocsf/v1_0_0/events/application_lifecycle.py
ocsf/v1_0_0/events/authentication.py
ocsf/v1_0_0/events/authorize_session.py
ocsf/v1_0_0/events/config_state.py
ocsf/v1_0_0/events/dhcp_activity.py
ocsf/v1_0_0/events/dns_activity.py
ocsf/v1_0_0/events/email_activity.py
ocsf/v1_0_0/events/email_file_activity.py
ocsf/v1_0_0/events/email_url_activity.py
ocsf/v1_0_0/events/entity_management.py
ocsf/v1_0_0/events/file_activity.py
ocsf/v1_0_0/events/ftp_activity.py
ocsf/v1_0_0/events/group_management.py
ocsf/v1_0_0/events/http_activity.py
ocsf/v1_0_0/events/inventory_info.py
ocsf/v1_0_0/events/kernel_activity.py
ocsf/v1_0_0/events/kernel_extension.py
ocsf/v1_0_0/events/memory_activity.py
ocsf/v1_0_0/events/module_activity.py
ocsf/v1_0_0/events/network_activity.py
ocsf/v1_0_0/events/network_file_activity.py
pydantic_ocsf-1.7.0.20260129.post1.dist-info/METADATA
pydantic_ocsf-1.7.0.20260129.post1.dist-info/WHEEL
pydantic_ocsf-1.7.0.20260129.post1.dist-info/licenses/LICENSE
pydantic_ocsf-1.7.0.20260129.post1.dist-info/RECORD
