Metadata-Version: 2.4
Name: pydantic-ocsf
Version: 1.7.0.20260129.post1
Summary: Pydantic models for the Open Cybersecurity Schema Framework (OCSF)
Project-URL: Homepage, https://github.com/mcm/pydantic-ocsf
Project-URL: Documentation, https://github.com/mcm/pydantic-ocsf#readme
Project-URL: Repository, https://github.com/mcm/pydantic-ocsf
Author-email: Your Name <you@example.com>
License-Expression: Apache-2.0
License-File: LICENSE
Keywords: cybersecurity,ocsf,pydantic,schema,security
Classifier: Development Status :: 4 - Beta
Classifier: Intended Audience :: Developers
Classifier: License :: OSI Approved :: Apache Software License
Classifier: Programming Language :: Python :: 3
Classifier: Programming Language :: Python :: 3.9
Classifier: Programming Language :: Python :: 3.10
Classifier: Programming Language :: Python :: 3.11
Classifier: Programming Language :: Python :: 3.12
Classifier: Programming Language :: Python :: 3.13
Classifier: Programming Language :: Python :: 3.14
Classifier: Topic :: Security
Classifier: Typing :: Typed
Requires-Python: >=3.9
Requires-Dist: eval-type-backport>=0.2.0; python_version < '3.10'
Requires-Dist: pydantic<3.0,>=2.5
Provides-Extra: dev
Requires-Dist: mypy>=1.0; extra == 'dev'
Requires-Dist: pytest-cov>=4.0; extra == 'dev'
Requires-Dist: pytest>=7.0; extra == 'dev'
Requires-Dist: ruff>=0.1; extra == 'dev'
Provides-Extra: generator
Requires-Dist: httpx>=0.25; extra == 'generator'
Requires-Dist: jinja2>=3.0; extra == 'generator'
